daisyflcocdrlib/__init__.py
daisyflcocdrlib/client/__init__.py
daisyflcocdrlib/client/app.py
daisyflcocdrlib/client/client.py
daisyflcocdrlib/client/client_operator_manager.py
daisyflcocdrlib/client/dpfedavg_numpy_client.py
daisyflcocdrlib/client/grpc_client/__init__.py
daisyflcocdrlib/client/grpc_client/c2z_connection.py
daisyflcocdrlib/client/grpc_client/message_handler.py
daisyflcocdrlib/client/grpc_server/__init__.py
daisyflcocdrlib/client/grpc_server/client_service_servicer.py
daisyflcocdrlib/client/grpc_server/grpc_server.py
daisyflcocdrlib/client/numpy_client.py
daisyflcocdrlib/client/trainer.py
daisyflcocdrlib/common/__init__.py
daisyflcocdrlib/common/dp.py
daisyflcocdrlib/common/logger.py
daisyflcocdrlib/common/metadata.py
daisyflcocdrlib/common/parameter.py
daisyflcocdrlib/common/serde.py
daisyflcocdrlib/common/typing.py
daisyflcocdrlib/master/__init__.py
daisyflcocdrlib/master/app.py
daisyflcocdrlib/master/grpc_server/__init__.py
daisyflcocdrlib/master/grpc_server/grpc_server.py
daisyflcocdrlib/master/grpc_server/master_service_servicer.py
daisyflcocdrlib/master/model.py
daisyflcocdrlib/master/server_api_handler.py
daisyflcocdrlib/master/test_mix.py
daisyflcocdrlib/operator/__init__.py
daisyflcocdrlib/operator/base/__init__.py
daisyflcocdrlib/operator/base/client_logic.py
daisyflcocdrlib/operator/base/server_logic.py
daisyflcocdrlib/operator/base_async/__init__.py
daisyflcocdrlib/operator/base_async/client_logic.py
daisyflcocdrlib/operator/base_async/server_logic.py
daisyflcocdrlib/operator/msg_demo/client_logic.py
daisyflcocdrlib/operator/msg_demo/msg.py
daisyflcocdrlib/operator/msg_demo/server_logic.py
daisyflcocdrlib/operator/msg_demo/zone_server_logic.py
daisyflcocdrlib/operator/sec_agg/client_logic.py
daisyflcocdrlib/operator/sec_agg/common.py
daisyflcocdrlib/operator/sec_agg/primitives.py
daisyflcocdrlib/operator/sec_agg/server_logic.py
daisyflcocdrlib/operator/strategy/__init__.py
daisyflcocdrlib/operator/strategy/aggregate.py
daisyflcocdrlib-0.0.8.dist-info/LICENSE
daisyflcocdrlib-0.0.8.dist-info/WHEEL
daisyflcocdrlib-0.0.8.dist-info/METADATA
daisyflcocdrlib-0.0.8.dist-info/RECORD
